GDELT21/__init__.py
GDELT21/setup.py
GDELT21/NG-headlines/NG-headlines.py
GDELT21/NG-headlines/__init__.py
GDELT21/NG-lda/NG-lda.py
GDELT21/NG-lda/__init__.py
GDELT21/NG-wordcloud/NG-wordcloud.py
GDELT21/NG-wordcloud/__init__.py
gdelt21-0.0.1.dist-info/METADATA
gdelt21-0.0.1.dist-info/WHEEL
gdelt21-0.0.1.dist-info/licenses/LICENSE.txt
gdelt21-0.0.1.dist-info/RECORD
